customblocks/__init__.py
customblocks/customblocks.py
customblocks/customblocks_test.py
customblocks/entrypoints.py
customblocks/generators.py
customblocks/generators_test.py
customblocks/testutils.py
customblocks/utils/__init__.py
customblocks/utils/fetcher.py
customblocks/utils/fetcher_test.py
customblocks/utils/hyperscript.py
customblocks/utils/hyperscript_test.py
customblocks/utils/image.py
customblocks/utils/image_test.py
customblocks/utils/pageinfo.py
customblocks/utils/pageinfo_test.py
markdown_customblocks-1.5.4.dist-info/licenses/LICENSE
markdown_customblocks-1.5.4.dist-info/METADATA
markdown_customblocks-1.5.4.dist-info/WHEEL
markdown_customblocks-1.5.4.dist-info/entry_points.txt
markdown_customblocks-1.5.4.dist-info/top_level.txt
markdown_customblocks-1.5.4.dist-info/RECORD
