Metadata-Version: 2.4
Name: markdown-customblocks
Version: 1.5.4
Summary: Python Markdown extension to add custom parametrizable and nestable blocks
Author-email: David García Garzón <voki@canvoki.net>
License:                     GNU AFFERO GENERAL PUBLIC LICENSE
Project-URL: Homepage, https://vokimon.github.io/markdown-customblocks
Project-URL: Documentation, https://vokimon.github.io/markdown-customblocks
Project-URL: Repository, https://github.com/vokimon/markdown-customblocks
Project-URL: Changelog, https://github.com/vokimon/markdown-customblocks/blob/master/CHANGES.md
Keywords: markdown,extension,customblocks,admonitions,container,figure,map,youtube,vimeo,twitter,facebook,instagram,verkami,goteo,mastodon,wikipedia,peertube
Classifier: Development Status :: 5 - Production/Stable
Classifier: Environment :: Console
Classifier: Intended Audience :: Developers
Classifier: Intended Audience :: Science/Research
Classifier: Intended Audience :: Other Audience
Classifier: License :: OSI Approved :: GNU Affero General Public License v3 or later (AGPLv3+)
Classifier: Operating System :: OS Independent
Classifier: Programming Language :: Python :: 3
Classifier: Programming Language :: Python :: 3.8
Classifier: Programming Language :: Python :: 3.9
Classifier: Programming Language :: Python :: 3.10
Classifier: Programming Language :: Python :: 3.11
Classifier: Programming Language :: Python :: 3.12
Classifier: Topic :: Internet :: WWW/HTTP :: Dynamic Content
Classifier: Topic :: Software Development :: Libraries :: Python Modules
Classifier: Topic :: Text Processing :: Filters
Classifier: Topic :: Text Processing :: Markup :: HTML
Requires-Python: >=3.8
License-File: LICENSE
Requires-Dist: markdown
Requires-Dist: yamlns>=0.11
Requires-Dist: beautifulsoup4
Requires-Dist: decorator
Requires-Dist: geocoder
Requires-Dist: pytest
Requires-Dist: pytest-cov<4
Requires-Dist: responses
Requires-Dist: python-magic
Requires-Dist: pillow
Dynamic: license-file
